rdf_construct/__init__.py
rdf_construct/__main__.py
rdf_construct/cli.py
rdf_construct/core/__init__.py
rdf_construct/core/config.py
rdf_construct/core/ordering.py
rdf_construct/core/predicate_order.py
rdf_construct/core/profile.py
rdf_construct/core/selector.py
rdf_construct/core/serialiser.py
rdf_construct/core/utils.py
rdf_construct/cq/__init__.py
rdf_construct/cq/expectations.py
rdf_construct/cq/formatters/__init__.py
rdf_construct/cq/formatters/json.py
rdf_construct/cq/formatters/junit.py
rdf_construct/cq/formatters/text.py
rdf_construct/cq/loader.py
rdf_construct/cq/runner.py
rdf_construct/describe/__init__.py
rdf_construct/describe/analyzer.py
rdf_construct/describe/documentation.py
rdf_construct/describe/formatters/__init__.py
rdf_construct/describe/formatters/json.py
rdf_construct/describe/formatters/markdown.py
rdf_construct/describe/formatters/text.py
rdf_construct/describe/hierarchy.py
rdf_construct/describe/imports.py
rdf_construct/describe/metadata.py
rdf_construct/describe/metrics.py
rdf_construct/describe/models.py
rdf_construct/describe/namespaces.py
rdf_construct/describe/profiles.py
rdf_construct/diff/__init__.py
rdf_construct/diff/change_types.py
rdf_construct/diff/comparator.py
rdf_construct/diff/filters.py
rdf_construct/diff/formatters/__init__.py
rdf_construct/diff/formatters/json.py
rdf_construct/diff/formatters/markdown.py
rdf_construct/diff/formatters/text.py
rdf_construct/docs/__init__.py
rdf_construct/docs/config.py
rdf_construct/docs/extractors.py
rdf_construct/docs/generator.py
rdf_construct/docs/renderers/__init__.py
rdf_construct/docs/renderers/html.py
rdf_construct/docs/renderers/json.py
rdf_construct/docs/renderers/markdown.py
rdf_construct/docs/search.py
rdf_construct/docs/templates/html/base.html.jinja
rdf_construct/docs/templates/html/class.html.jinja
rdf_construct/docs/templates/html/hierarchy.html.jinja
rdf_construct/docs/templates/html/index.html.jinja
rdf_construct/docs/templates/html/instance.html.jinja
rdf_construct-0.4.1.dist-info/METADATA
rdf_construct-0.4.1.dist-info/WHEEL
rdf_construct-0.4.1.dist-info/entry_points.txt
rdf_construct-0.4.1.dist-info/licenses/LICENSE
rdf_construct-0.4.1.dist-info/RECORD
