Metadata-Version: 2.4
Name: rdf-construct
Version: 0.4.1
Summary: Semantic RDF manipulation toolkit - order, serialize, and diff RDF ontologies
License-Expression: MIT
License-File: LICENSE
Keywords: rdf,ontology,turtle,owl,rdfs,knowledge-graph,knowledge-base,serialization,ontology-engineering,ontology-management,sparql
Author: Dave Dyke
Author-email: 23141680+aigora-de@users.noreply.github.com
Maintainer: Dave Dyke
Maintainer-email: 23141680+aigora-de@users.noreply.github.com
Requires-Python: >=3.10
Classifier: Development Status :: 4 - Beta
Classifier: Intended Audience :: Developers
Classifier: Intended Audience :: Science/Research
Classifier: Intended Audience :: Information Technology
Classifier: Operating System :: OS Independent
Classifier: Programming Language :: Python :: 3
Classifier: Programming Language :: Python :: 3.10
Classifier: Programming Language :: Python :: 3.11
Classifier: Programming Language :: Python :: 3.12
Classifier: Topic :: Scientific/Engineering :: Information Analysis
Classifier: Topic :: Software Development :: Libraries :: Python Modules
Classifier: Topic :: Internet :: WWW/HTTP
Classifier: Topic :: Text Processing :: Markup
Classifier: Typing :: Typed
Requires-Dist: click (>=8.1.0,<9.0.0)
Requires-Dist: jinja2 (>=3.1.0,<4.0.0)
Requires-Dist: pyyaml (>=6.0,<7.0)
Requires-Dist: rdflib (>=7.0.0,<8.0.0)
Requires-Dist: rich (>=13.0.0,<14.0.0)
Project-URL: Bug Tracker, https://github.com/aigora-de/rdf-construct/issues
Project-URL: Changelog, https://github.com/aigora-de/rdf-construct/blob/main/CHANGELOG.md
Project-URL: Documentation, https://github.com/aigora-de/rdf-construct#readme
Project-URL: Homepage, https://github.com/aigora-de/rdf-construct
Project-URL: Repository, https://github.com/aigora-de/rdf-construct.git
